{
  "project_info": {
    "project_number": "292032205715",
    "firebase_url": "https://hackhealth-c0852.firebaseio.com",
    "project_id": "hackhealth-c0852",
    "storage_bucket": "hackhealth-c0852.appspot.com"
  },
  "client": [
    {
      "client_info": {
        "mobilesdk_app_id": "1:292032205715:android:5f47be6dbaa85caa",
        "android_client_info": {
          "package_name": "hackhealth2018.hackhealth2018"
        }
      },
      "oauth_client": [
        {
          "client_id": "292032205715-lgn85rrjulqp6m8pulcrnqbsma5c78oo.apps.googleusercontent.com",
          "client_type": 3
        }
      ],
      "api_key": [
        {
          "current_key": "AIzaSyAB4ecu85UO4E-q44zP5c83RBolWhb22C8"
        }
      ],
      "services": {
        "analytics_service": {
          "status": 1
        },
        "appinvite_service": {
          "status": 1,
          "other_platform_oauth_client": []
        },
        "ads_service": {
          "status": 2
        }
      }
    }
  ],
  "configuration_version": "1"
}